pullsaw/__init__.py
pullsaw/claude_code.py
pullsaw/config.py
pullsaw/constants.py
pullsaw/executor.py
pullsaw/git_ops.py
pullsaw/main.py
pullsaw/models.py
pullsaw/pathspec.py
pullsaw/session.py
pullsaw-0.1.0.dist-info/METADATA
pullsaw-0.1.0.dist-info/WHEEL
pullsaw-0.1.0.dist-info/entry_points.txt
pullsaw-0.1.0.dist-info/licenses/LICENSE
pullsaw-0.1.0.dist-info/RECORD
