Metadata-Version: 2.4
Name: pullsaw
Version: 0.1.0
Summary: Split large PRs into stacked PRs using Claude Code
License-File: LICENSE
Requires-Python: >=3.12
Requires-Dist: click>=8.0
Requires-Dist: pyyaml>=6.0
Requires-Dist: rich>=13.0
Provides-Extra: dev
Requires-Dist: mypy>=1.0; extra == 'dev'
Requires-Dist: pytest-cov>=4.0; extra == 'dev'
Requires-Dist: pytest>=8.0; extra == 'dev'
Requires-Dist: ruff>=0.8; extra == 'dev'
Requires-Dist: types-pyyaml>=6.0; extra == 'dev'
